branch_and_bound/__init__.py
branch_and_bound/branch_and_bound.py
branch_and_bound_feature_selection-0.3.dist-info/METADATA
branch_and_bound_feature_selection-0.3.dist-info/RECORD
branch_and_bound_feature_selection-0.3.dist-info/WHEEL
branch_and_bound_feature_selection-0.3.dist-info/top_level.txt
