Metadata-Version: 2.1
Name: branch-and-bound-feature-selection
Version: 0.3
Summary: Implementation of Backward Feature Selection using "Branch and Bound"
Home-page: https://github.com/MaximilianIdahl/branch-and-bound-feature-selection
Author: Maximilian Idahl
Author-email: max@idahl.de
License: MIT
Keywords: feature selection,branch and bound,branch,bound,backward,eliminaton
Platform: UNKNOWN
Requires-Dist: numpy (>=1.13)
Requires-Dist: scikit-learn (>=0.19)
